pymialsrtk/__init__.py
pymialsrtk/info.py
pymialsrtk/parser.py
pymialsrtk/utils.py
pymialsrtk/bids/__init__.py
pymialsrtk/bids/utils.py
pymialsrtk/cli/__init__.py
pymialsrtk/cli/mialsuperresolutiontoolkit_docker.py
pymialsrtk/cli/mialsuperresolutiontoolkit_singularity.py
pymialsrtk/interfaces/__init__.py
pymialsrtk/interfaces/postprocess.py
pymialsrtk/interfaces/preprocess.py
pymialsrtk/interfaces/reconstruction.py
pymialsrtk/interfaces/utils.py
pymialsrtk/pipelines/__init__.py
pymialsrtk/pipelines/anatomical/__init__.py
pymialsrtk/pipelines/anatomical/abstract.py
pymialsrtk/pipelines/anatomical/preprocessing.py
pymialsrtk/pipelines/anatomical/srr.py
pymialsrtk/sphinxext/__init__.py
pymialsrtk/sphinxext/documenter.py
pymialsrtk/sphinxext/gh.py
pymialsrtk-2.1.0.dist-info/LICENSE.txt
pymialsrtk-2.1.0.dist-info/METADATA
pymialsrtk-2.1.0.dist-info/WHEEL
pymialsrtk-2.1.0.dist-info/entry_points.txt
pymialsrtk-2.1.0.dist-info/top_level.txt
pymialsrtk-2.1.0.dist-info/RECORD
