Metadata-Version: 2.1
Name: pymialsrtk
Version: 2.1.0
Summary: PyMIALSRTK: Nipype pipelines for the MIAL Super Resolution Toolkit
Home-page: https://github.com/Medical-Image-Analysis-Laboratory/mialsuperresolutiontoolkit
Author: Sebastien Tourbier
Author-email: sebastien.tourbier@alumni.epfl.ch
Maintainer: Medical Image Analysis Laboratory, University Hospital of Lausanne and the MIALSRTK developers
Maintainer-email: sebastien.tourbier@alumni.epfl.ch
License: BSD-3-Clause
Platform: UNKNOWN
Classifier: Development Status :: 5 - Production/Stable
Classifier: Intended Audience :: Science/Research
Classifier: Intended Audience :: Developers
Classifier: License :: OSI Approved
Classifier: Programming Language :: C++
Classifier: Programming Language :: Python
Classifier: Topic :: Software Development
Classifier: Topic :: Scientific/Engineering :: Image Processing
Classifier: Operating System :: Microsoft :: Windows
Classifier: Operating System :: POSIX
Classifier: Operating System :: Unix
Classifier: Operating System :: MacOS
Classifier: Programming Language :: Python :: 3.6
Classifier: Programming Language :: Python :: 3.7
Requires-Python: >=3.6
License-File: LICENSE.txt
Requires-Dist: codecarbon (==1.2.0)
Requires-Dist: dash-bootstrap-components (==0.13.1)
